starscode/__init__.py
starscode-0.1.dist-info/LICENCE.txt
starscode-0.1.dist-info/METADATA
starscode-0.1.dist-info/WHEEL
starscode-0.1.dist-info/top_level.txt
starscode-0.1.dist-info/RECORD
